pydpaux/__init__.py
pydpaux/__init__.pyi
pydpaux/_core.cp39-win_amd64.pyd
pydpaux-0.1.1.dist-info/METADATA
pydpaux-0.1.1.dist-info/WHEEL
pydpaux-0.1.1.dist-info/licenses/LICENSE
pydpaux-0.1.1.dist-info/RECORD
