Metadata-Version: 2.2
Name: pydpaux
Version: 0.1.1
Summary: A Python wrapper for accessing DP/eDP-connected displays via AUX lines using SoC vendor-specific APIs.
Classifier: Programming Language :: Python :: 3
Classifier: License :: OSI Approved :: MIT License
Classifier: Operating System :: Microsoft :: Windows :: Windows 10
Classifier: Operating System :: Microsoft :: Windows :: Windows 11
Project-URL: Source, https://github.com/bitlab-rgb/pydpaux
Requires-Python: >=3.9
Requires-Dist: numpy>=2.0.0
